mlops/Experiment.py
mlops/ProjectFile.py
mlops/__init__.py
mlops/_version.py
mlops/cli.py
mlops/release/Release.py
mlops/release/__init__.py
mlops/release/destinations/LocalDestination.py
mlops/release/destinations/ReleaseDestination.py
mlops/release/destinations/SharepointDestination.py
mlops/release/destinations/ZenodoDestination.py
mlops/release/destinations/__init__.py
mlops/release/sources/LocalSource.py
mlops/release/sources/MLFlowSource.py
mlops/release/sources/ReleaseSource.py
mlops/release/sources/__init__.py
mlops/utils/Config.py
mlops/utils/__init__.py
tests/__init__.py
tests/mlflow_server/__init__.py
tests/mlflow_server/test_server.py
tests/mlops/__init__.py
tests/mlops/test_Experiment.py
tests/mlops/test_cli.py
tests/mlops/release/__init__.py
tests/mlops/release/test_Release.py
tests/mlops/release/destinatons/__init__.py
tests/mlops/release/destinatons/test_LocalDestination.py
tests/mlops/release/destinatons/test_ReleaseDestination.py
tests/mlops/release/destinatons/test_SharepointDestination.py
tests/mlops/release/sources/__init__.py
tests/mlops/release/sources/test_MLFlowSource.py
tests/mlops/release/sources/test_ReleaseSource.py
csc_mlops-0.9.23.dist-info/LICENSE
csc_mlops-0.9.23.dist-info/METADATA
csc_mlops-0.9.23.dist-info/WHEEL
csc_mlops-0.9.23.dist-info/entry_points.txt
csc_mlops-0.9.23.dist-info/top_level.txt
csc_mlops-0.9.23.dist-info/RECORD
