Metadata-Version: 2.1
Name: csc-mlops
Version: 0.9.23
Summary: An MLOps framework for development of clinical applications
Home-page: https://github.com/GSTT-CSC/MLOps
Author: GSTT-CSC
Author-email: ClinicalScientificComputing@gstt.nhs.uk
Requires-Python: <3.12
License-File: LICENSE
Requires-Dist: mlflow ==2.10.0
Requires-Dist: boto3
Requires-Dist: docker
Requires-Dist: minio
Requires-Dist: colorlog
Requires-Dist: monai
Requires-Dist: itk
Requires-Dist: pandas
Requires-Dist: matplotlib
Requires-Dist: xnat
Requires-Dist: GitPython
Requires-Dist: PyYAML
Requires-Dist: click
Requires-Dist: tqdm
Requires-Dist: requests ==2.31.0
